solid_i18n/__init__.py
solid_i18n/contrib.py
solid_i18n/memory.py
solid_i18n/middleware.py
solid_i18n/urlresolvers.py
solid_i18n/urls.py
solid_i18n-1.4.2.dist-info/DESCRIPTION.rst
solid_i18n-1.4.2.dist-info/METADATA
solid_i18n-1.4.2.dist-info/RECORD
solid_i18n-1.4.2.dist-info/WHEEL
solid_i18n-1.4.2.dist-info/metadata.json
solid_i18n-1.4.2.dist-info/top_level.txt
