Metadata-Version: 2.0
Name: solid-i18n
Version: 1.4.2
Summary: Use default language for urls without language prefix (django)
Home-page: https://github.com/st4lk/django-solid-i18n-urls
Author: st4lk
Author-email: alexevseev@gmail.com
License: BSD License
Keywords: django,i18n,urls,solid,redirects,language,default
Platform: Any
Classifier: Environment :: Web Environment
Classifier: Framework :: Django
Classifier: Intended Audience :: Developers
Classifier: License :: OSI Approved :: BSD License
Classifier: Operating System :: OS Independent
Classifier: Programming Language :: Python
Classifier: Topic :: Utilities
Requires-Dist: django (>=1.8)
